vbuild/__init__.py
vbuild-0.8.1.dist-info/LICENSE
vbuild-0.8.1.dist-info/WHEEL
vbuild-0.8.1.dist-info/METADATA
vbuild-0.8.1.dist-info/RECORD
